rbfopt/__init__.py
rbfopt/rbfopt_algorithm.py
rbfopt/rbfopt_aux_problems.py
rbfopt/rbfopt_black_box.py
rbfopt/rbfopt_cl_interface.py
rbfopt/rbfopt_degree0_models.py
rbfopt/rbfopt_degree1_models.py
rbfopt/rbfopt_degreem1_models.py
rbfopt/rbfopt_refinement.py
rbfopt/rbfopt_settings.py
rbfopt/rbfopt_test_functions.py
rbfopt/rbfopt_test_interface.py
rbfopt/rbfopt_user_black_box.py
rbfopt/rbfopt_utils.py
rbfopt/doc/Makefile
rbfopt/doc/conf.py
rbfopt/doc/index.rst
rbfopt/doc/make.bat
rbfopt/doc/rbfopt_algorithm.rst
rbfopt/doc/rbfopt_aux_problems.rst
rbfopt/doc/rbfopt_black_box.rst
rbfopt/doc/rbfopt_degree0_models.rst
rbfopt/doc/rbfopt_degree1_models.rst
rbfopt/doc/rbfopt_degreem1_models.rst
rbfopt/doc/rbfopt_refinement.rst
rbfopt/doc/rbfopt_settings.rst
rbfopt/doc/rbfopt_test_functions.rst
rbfopt/doc/rbfopt_user_black_box.rst
rbfopt/doc/rbfopt_utils.rst
rbfopt/examples/rbfopt_black_box_example.py
rbfopt-4.3.0.dist-info/licenses/AUTHORS
rbfopt-4.3.0.dist-info/licenses/LICENSE
rbfopt-4.3.0.dist-info/METADATA
rbfopt-4.3.0.dist-info/WHEEL
rbfopt-4.3.0.dist-info/entry_points.txt
rbfopt-4.3.0.dist-info/top_level.txt
rbfopt-4.3.0.dist-info/RECORD
