Metadata-Version: 2.4
Name: rbfopt
Version: 4.3.0
Summary: RBFOpt is a library for black-box optimization using derivative-free optimization tools.
Author-email: Giacomo Nannicini <g.nannicini@usc.edu>
Maintainer-email: Giacomo Nannicini <g.nannicini@usc.edu>
License: Copyright (c) 2014-2025, Singapore University of Technology and Design
Project-URL: Homepage, https://github.com/coin-or/rbfopt
Project-URL: Bug Reports, https://github.com/coin-or/rbfopt/issues
Classifier: Development Status :: 5 - Production/Stable
Classifier: License :: OSI Approved :: BSD License
Classifier: Programming Language :: Python :: 3
Classifier: Programming Language :: Python :: 3.9
Classifier: Programming Language :: Python :: 3.10
Classifier: Programming Language :: Python :: 3.11
Classifier: Programming Language :: Python :: 3.12
Classifier: Programming Language :: Python :: 3.13
Classifier: Programming Language :: Python :: 3 :: Only
Classifier: Topic :: Scientific/Engineering :: Mathematics
Requires-Python: >=3.9
License-File: LICENSE
License-File: AUTHORS
Requires-Dist: numpy>=2.0.0
Requires-Dist: scipy>=1.13.0
Requires-Dist: numpydoc>=0.5
Requires-Dist: pyomo>=5.1.1
Provides-Extra: test
Requires-Dist: mock>=1.1.3; extra == "test"
Requires-Dist: pytest; extra == "test"
Dynamic: license-file
